{
	"instance" : {
		"writeString:" : "MasashiUmezawa 5/21/2015 22:04",
		"canvas:" : "MasashiUmezawa 5/20/2015 22:02",
		"visitHtmlEscapedToken:" : "MasashiUmezawa 5/20/2015 22:03",
		"context:" : "MasashiUmezawa 5/20/2015 22:00",
		"renderSection:withObject:" : "MasashiUmezawa 5/20/2015 23:18",
		"visitSection:" : "ShoYoshida 5/30/2015 16:55",
		"renderSection:withBlock:" : "MasashiUmezawa 5/21/2015 12:56",
		"partialAt:" : "MasashiUmezawa 1/29/2016 16:21",
		"visitStringChunk:" : "MasashiUmezawa 5/20/2015 23:35"
	},
	"class" : { }
}